<?xml version="1.0" encoding="utf-8" standalone="no"?>
<vehicle type="pallet" parentFile="$data/objects/pallets/fertilizer/fertilizer.xml">
    <storeData>
        <name>$l10n_sf_potash_title</name>
        <price>1800</price>
        <category>misc</category>
        <image>$data/store/items/fertilizer/fertilizer_standard.png</image>
        <specs>
            <fillType>POTASH</fillType>
        </specs>
    </storeData>
    <fillUnit>
        <fillVolumes>
            <fillVolume fillTypes="POTASH" capacity="800"/>
        </fillVolumes>
    </fillUnit>
</vehicle>
